darknet/__init__.py
darknet/py/__init__.py
darknet/py/__main__.py
darknet/py/_version.py
darknet/py/classifier.py
darknet/py/cli.py
darknet/py/detector.py
darknet/py/intake.py
darknet/py/network.pyx
darknet/py/util.py
darknet/sagemaker/__init__.py
darknet/sagemaker/__main__.py
darknet/sagemaker/default_inference_handler.py
darknet/sagemaker/classifier/__init__.py
darknet/sagemaker/classifier/__main__.py
darknet/sagemaker/classifier/default_inference_handler.py
darknet/sagemaker/classifier/handler_service.py
darknet/sagemaker/detector/__init__.py
darknet/sagemaker/detector/__main__.py
darknet/sagemaker/detector/default_inference_handler.py
darknet/sagemaker/detector/handler_service.py
darknet/zoo/__init__.py
darknet/zoo/darknet.yaml
darknet/zoo/imagenet.yaml
libdarknet/__init__.pxd
darknet.py-0.3.0.dist-info/LICENSE
darknet.py-0.3.0.dist-info/METADATA
darknet.py-0.3.0.dist-info/WHEEL
darknet.py-0.3.0.dist-info/entry_points.txt
darknet.py-0.3.0.dist-info/top_level.txt
darknet.py-0.3.0.dist-info/RECORD
