Metadata-Version: 2.1
Name: darknet.py
Version: 0.3.0
Summary: DarkNet OpenSource Neural Networks in Python
Home-page: https://github.com/zeroae/darknet.py
Author: Patrick Sodré
Author-email: psodre@gmail.com
License: MIT
Keywords: py darknet
Platform: UNKNOWN
Classifier: Development Status :: 2 - Pre-Alpha
Classifier: Intended Audience :: Developers
Classifier: License :: OSI Approved :: MIT License
Classifier: Natural Language :: English
Classifier: Programming Language :: Python :: 3
Classifier: Programming Language :: Python :: 3.6
Classifier: Programming Language :: Python :: 3.7
Classifier: Programming Language :: Python :: 3.8
Requires-Python: >=3.6
License-File: LICENSE
Requires-Dist: click (>=7.0)
Requires-Dist: click-plugins
Requires-Dist: entrypoints
Requires-Dist: fsspec (<=0.7.5)
Requires-Dist: numpy
Requires-Dist: pillow
Provides-Extra: doc
Requires-Dist: sphinx ; extra == 'doc'
Requires-Dist: sphinx-autoapi ; extra == 'doc'
Requires-Dist: sphinx-click ; extra == 'doc'
Requires-Dist: watchdog ; extra == 'doc'
Provides-Extra: mms
Requires-Dist: future ; extra == 'mms'
Requires-Dist: multi-model-server ; extra == 'mms'
Requires-Dist: retrying ; extra == 'mms'
Requires-Dist: sagemaker-inference ; extra == 'mms'
Provides-Extra: test
Requires-Dist: pytest (>=3) ; extra == 'test'
Requires-Dist: pytest-cov ; extra == 'test'
Requires-Dist: pytest-mock ; extra == 'test'
Provides-Extra: zoo
Requires-Dist: intake ; extra == 'zoo'
